bloqzapi/__init__.py
bloqzapi/client.py
bloqzapi-1.1.0.dist-info/METADATA
bloqzapi-1.1.0.dist-info/WHEEL
bloqzapi-1.1.0.dist-info/top_level.txt
bloqzapi-1.1.0.dist-info/RECORD
