Metadata-Version: 2.4
Name: bloqzapi
Version: 1.1.0
Summary: Bloqz Intent API SDK - Convert financial intent from natural language into deterministic execution plans
Author-email: Bloqz <support@bloqz.io>
License: UNLICENSED
Project-URL: Homepage, https://bloqz.io
Project-URL: Repository, https://github.com/bloqz/bloqzapi
Project-URL: Documentation, https://bloqz.io/docs
Keywords: bloqz,intent,defi,blockchain,api,sdk
Classifier: Development Status :: 4 - Beta
Classifier: Intended Audience :: Developers
Classifier: Programming Language :: Python :: 3
Classifier: Programming Language :: Python :: 3.9
Classifier: Programming Language :: Python :: 3.10
Classifier: Programming Language :: Python :: 3.11
Classifier: Programming Language :: Python :: 3.12
Requires-Python: >=3.9
Requires-Dist: requests>=2.31.0
